drf_cached_instances/__init__.py
drf_cached_instances/cache.py
drf_cached_instances/compat.py
drf_cached_instances/mixins.py
drf_cached_instances/models.py
drf_cached_instances-0.3.4.dist-info/DESCRIPTION.rst
drf_cached_instances-0.3.4.dist-info/METADATA
drf_cached_instances-0.3.4.dist-info/RECORD
drf_cached_instances-0.3.4.dist-info/WHEEL
drf_cached_instances-0.3.4.dist-info/metadata.json
drf_cached_instances-0.3.4.dist-info/top_level.txt
