Metadata-Version: 1.1
Name: drf-cached-instances
Version: 0.3.4
Summary: Cached instances for Django REST Framework
Home-page: https://github.com/jwhitlock/drf-cached-instances
Author: John Whitlock
Author-email: john@factorialfive.com
License: MPL 2.0
Keywords: drf-cached-instances
Platform: UNKNOWN
Classifier: Development Status :: 4 - Beta
Classifier: Framework :: Django
Classifier: Intended Audience :: Developers
Classifier: License :: OSI Approved :: Mozilla Public License 2.0 (MPL 2.0)
Classifier: Natural Language :: English
Classifier: Programming Language :: Python :: 2
Classifier: Programming Language :: Python :: 2.7
Classifier: Programming Language :: Python :: 3
Classifier: Programming Language :: Python :: 3.3
Classifier: Programming Language :: Python :: 3.4
Classifier: Programming Language :: Python :: 3.5
